lrparse/__init__.py
lrparse/_lrparse.cp313-win_amd64.pyd
lrparse/lrparse.c
lrparse-0.1.8.dist-info/METADATA
lrparse-0.1.8.dist-info/WHEEL
lrparse-0.1.8.dist-info/top_level.txt
lrparse-0.1.8.dist-info/RECORD
