Metadata-Version: 2.4
Name: lrparse
Version: 0.1.8
Summary: Left/right substring extraction
Author-email: Long Le Nhat <longnhatleeee02@gmail.com>
License-Expression: MIT
Project-URL: Documentation, https://github.com/haohanxabo1/lrparse
Classifier: Programming Language :: Python :: 3
Classifier: Programming Language :: C
Requires-Python: >=3.8
